proc_tap-1.0.3.dist-info/licenses/LICENSE
proctap/__init__.py
proctap/__main__.py
proctap/_native.pyi
proctap/_version.py
proctap/core.py
proctap/backends/__init__.py
proctap/backends/base.py
proctap/backends/converter.py
proctap/backends/linux.py
proctap/backends/macos_pyobjc.py
proctap/backends/macos_screencapture.py
proctap/backends/pipewire_native.py
proctap/backends/windows.py
proctap/contrib/__init__.py
proctap/contrib/analysis.py
proctap/contrib/discord_source.py
proctap/contrib/whisper_transcribe.py
proctap/contrib/filters/__init__.py
proctap/contrib/filters/base.py
proctap/contrib/filters/chain.py
proctap/contrib/filters/dsp.py
proctap/contrib/filters/dynamics.py
proctap/contrib/filters/vad.py
proctap/swift/screencapture-audio/Package.swift
proctap/swift/screencapture-audio/Sources/screencapture-audio/main.swift
proc_tap-1.0.3.dist-info/METADATA
proc_tap-1.0.3.dist-info/WHEEL
proc_tap-1.0.3.dist-info/entry_points.txt
proc_tap-1.0.3.dist-info/top_level.txt
proc_tap-1.0.3.dist-info/RECORD
