Metadata-Version: 2.4
Name: proc-tap
Version: 1.0.3
Summary: Cross-platform process-level audio capture library
Author-email: m96-chan <y_harada@technologies.moe>
License-Expression: MIT
Project-URL: Homepage, https://github.com/m96-chan/ProcTap
Project-URL: Repository, https://github.com/m96-chan/ProcTap
Project-URL: Issues, https://github.com/m96-chan/ProcTap/issues
Keywords: audio,capture,wasapi,windows,linux,macos,pulseaudio,coreaudio,process,loopback
Classifier: Development Status :: 4 - Beta
Classifier: Intended Audience :: Developers
Classifier: Operating System :: Microsoft :: Windows
Classifier: Operating System :: Microsoft :: Windows :: Windows 10
Classifier: Operating System :: Microsoft :: Windows :: Windows 11
Classifier: Operating System :: POSIX :: Linux
Classifier: Operating System :: MacOS
Classifier: Operating System :: MacOS :: MacOS X
Classifier: Programming Language :: Python :: 3
Classifier: Programming Language :: Python :: 3.10
Classifier: Programming Language :: Python :: 3.11
Classifier: Programming Language :: Python :: 3.12
Classifier: Programming Language :: Python :: 3.13
Classifier: Programming Language :: C++
Classifier: Topic :: Multimedia :: Sound/Audio :: Capture/Recording
Classifier: Topic :: Software Development :: Libraries :: Python Modules
Requires-Python: >=3.10
License-File: LICENSE
Requires-Dist: numpy>=1.20.0
Requires-Dist: scipy>=1.7.0
Requires-Dist: pulsectl>=23.5.0; sys_platform == "linux"
Requires-Dist: pyobjc-core>=9.0; sys_platform == "darwin"
Requires-Dist: pyobjc-framework-CoreAudio>=9.0; sys_platform == "darwin"
Provides-Extra: dev
Requires-Dist: pytest; extra == "dev"
Requires-Dist: mypy; extra == "dev"
Requires-Dist: types-setuptools; extra == "dev"
Requires-Dist: types-psutil; extra == "dev"
Requires-Dist: scipy-stubs; extra == "dev"
Provides-Extra: docs
Requires-Dist: mkdocs-material>=9.0.0; extra == "docs"
Requires-Dist: mkdocstrings[python]>=0.24.0; extra == "docs"
Provides-Extra: linux
Requires-Dist: pulsectl>=23.5.0; extra == "linux"
Provides-Extra: contrib
Requires-Dist: faster-whisper>=1.0.0; extra == "contrib"
Provides-Extra: hq-resample
Requires-Dist: samplerate>=0.1.0; (python_version < "3.13" or sys_platform != "win32") and extra == "hq-resample"
Dynamic: license-file
